glp/__init__.py
glp/constraint.py
glp/core.py
glp/core_with_bigM.py
glp/enums.py
glp/goal.py
pygulp-0.1.1.dist-info/licenses/LICENSE
pygulp-0.1.1.dist-info/METADATA
pygulp-0.1.1.dist-info/WHEEL
pygulp-0.1.1.dist-info/top_level.txt
pygulp-0.1.1.dist-info/RECORD
