Metadata-Version: 2.4
Name: pygulp
Version: 0.1.1
Summary: Python Package for Goal Linear Programming
Author-email: AIDE Lab <info.aidelab@gmail.com>, Kshitij Vaidya <22b1829@iitb.ac.in>, Ishan Pandit <22b2141@iitb.ac.in>, Roomani Srivastava <roomani@iitb.ac.in>
Project-URL: Homepage, https://github.com/aidelab-iitbombay/GLP
Classifier: Programming Language :: Python :: 3
Classifier: Operating System :: OS Independent
Requires-Python: >=3.9
License-File: LICENSE
Requires-Dist: pulp
Provides-Extra: viz
Requires-Dist: pandas; extra == "viz"
Requires-Dist: matplotlib; extra == "viz"
Provides-Extra: dev
Requires-Dist: pytest; extra == "dev"
Requires-Dist: pytest-cov; extra == "dev"
Requires-Dist: black; extra == "dev"
Requires-Dist: ruff; extra == "dev"
Requires-Dist: mypy; extra == "dev"
Requires-Dist: pre-commit; extra == "dev"
Requires-Dist: twine; extra == "dev"
Requires-Dist: build; extra == "dev"
Requires-Dist: sphinx; extra == "dev"
Dynamic: license-file
